{
    "theme": {
        "colors": {
            "primary": "#624100",
            "secondary": "#867555",
            "background": "#FFEECA"
        }
    },
    "title": "반려견 MBTI 테스트",
    "subtitle": "우리집 반려견은 어떤 성향일까요?",
    "mainImage": "",
    "questions": [
        {
            "id": 0,
            "question": "처음보는 강아지 발견!",
            "answers": [
                {
                    "type": "e",
                    "text": "친구 조아! 바로 꼬리를 흔들며 달려간다."
                },
                {
                    "type": "i",
                    "text": "반갑지만.. 낯선 친구는 가까이 가기 어려운걸"
                }
            ]
        },
        {
            "id": 1,
            "question": "우리집 반려견은 밥을 먹을 때",
            "answers": [
                {
                    "type": "p",
                    "text": "무조건 한번에 다 먹는다"
                },
                {
                    "type": "j",
                    "text": "알아서 나누어 먹는다"
                }
            ]
        },
        {
            "id": 2,
            "question": "산책할 때의 반려견은",
            "answers": [
                {
                    "type": "s",
                    "text": "아는 길로 가자 집사야"
                },
                {
                    "type": "n",
                    "text": "저기 내가 좋아하는 냄새가 난다! 가보자!"
                }
            ]
        },
        {
            "id": 3,
            "question": "집사가 울고있을 때,",
            "answers": [
                {
                    "type": "f",
                    "text": "옆에서 함께 있어준다."
                },
                {
                    "type": "t",
                    "text": "집사가 좋아하는 물건을 가져온다."
                }
            ]
        }
    ],
    "results": {
        "infp": {
            "title": "몽상가 댕댕이",
            "subtitle": "가끔 창문밖을 바라보며 생각에 잠기는 . . .",
            "description": "조용한 공간에서 집사와 함께 힐링하는 것을 최고로 좋아하는 낭만있는 우리집 반려견",
            "image": ""
        },
        "infj": {
            "title": "해결사 댕댕이",
            "subtitle": "집사가 필요한 걸 빠르게 캐치하는 . . .",
            "description": "예민하고 섬세한 성격으로 집사의 해결사 역할을 해주는 우리집 반려견!",
            "image": ""
        },
        "intp": {
            "title": "개인주의 댕댕이",
            "subtitle": "나만의 공간이 중요해!",
            "description": "집사와 함께하는 시간도 좋지만, 가끔은 나만의 공간에서 조용히 지내고 싶어!",
            "image": ""
        },
        "intj": {
            "title": "완벽주의 댕댕이",
            "subtitle": "산책과 밥은 정해진 시간에 주세요!",
            "description": "본인이 세운 계획이 틀어지는 것을 좋아하지 않아요.",
            "image": ""
        },
        "isfp": {
            "title": "귀차니즘 댕댕이",
            "subtitle": "침대 위가 제일 좋아!",
            "description": "자꾸 제 이름을 부르지마세요. . . 침대에 좀만 더 누워있고 싶어요.",
            "image": ""
        },
        "isfj": {
            "title": "신중한 댕댕이",
            "subtitle": "반복적이고 익숙한 일이 좋아. . .",
            "description": "일관적이지 않은 집사의 모습에 당황할 수 있어요!",
            "image": ""
        },
        "istp": {
            "title": "집중력 좋은 댕댕이",
            "subtitle": "집중력 뿜뿜",
            "description": "집사와 함께하는 훈련시간! 집중력을 발휘해서 빠르게 습득하는 우리집 반려견",
            "image": ""
        },
        "istj": {
            "title": "정직한 댕댕이",
            "subtitle": "규칙을 잘 지키는. . .",
            "description": "집사가 실수로 두고 간 간식이라도 절대 허락 없이는 먹지 않는 우리집 반려견",
            "image": ""
        },
        "enfp": {
            "title": "인싸 댕댕이",
            "subtitle": "우리동네 핵인싸 댕댕이",
            "description": "동네에 모르는 친구가 없는 우리집 반려견",
            "image": ""
        },
        "enfj": {
            "title": "정의로운 댕댕이",
            "subtitle": "싸우지마 친구들아..",
            "description": "친구들이 싸우는 건 절대 못봐! 내가 도와줄게 친구들아!",
            "image": ""
        },
        "entp": {
            "title": "솔직한 댕댕이",
            "subtitle": "집사야 이 사료 맛없다!",
            "description": "취향이 확고한 우리집 반려견. 이 사료는 싫고, 저 사료는 좋아!",
            "image": ""
        },
        "entj": {
            "title": "리더 댕댕이",
            "subtitle": "카리스마 뿜뿜",
            "description": "당당하고 자신감 넘치는 리더 재질 우리집 반려견",
            "image": ""
        },
        "esfp": {
            "title": "사랑꾼 댕댕이",
            "subtitle": "집사를 누구보다 좋아해!",
            "description": "한 번 마음을 주면 누구보다 사랑해 줄 수 있어!",
            "image": ""
        },
        "esfj": {
            "title": "리액션 좋은 댕댕이",
            "subtitle": "꺅 간식이다!",
            "description": "간식 좋아!! 저 친구 너무 귀엽다!! 오늘 날씨도 너무 좋아!!",
            "image": ""
        },
        "estp": {
            "title": "자유로운 댕댕이",
            "subtitle": "다른집 반려견과는 어딘가 다른. . .",
            "description": "대문이 열려있다면 혼자 산책하고 돌아올 것 같은 우리집 반려견",
            "image": ""
        },
        "estj": {
            "title": "모험을 즐기는 댕댕이",
            "subtitle": "오감을 통해 얻는 정보가 최고야!",
            "description": "집사야 등산도 가고, 바다도 가고, 다양한 경험을 하고싶어!",
            "image": ""
        }
    }
}